{
  "light": {
    "--color-primary": "#2563eb",
    "--color-primary-hover": "#1d4ed8",
    "--color-secondary": "#3b82f6",
    "--color-cta": "#c2410c",
    "--color-cta-hover": "#9a3412",
    "--color-bg": "#f8fafc",
    "--color-surface": "#ffffff",
    "--color-text": "#1e293b",
    "--color-text-muted": "#475569",
    "--color-border": "#e2e8f0",
    "--shadow-card": "0 4px 6px -1px rgb(15 23 42 / 0.08), 0 2px 4px -2px rgb(15 23 42 / 0.06)",
    "--radius-md": "12px",
    "--radius-lg": "16px",
    "--font-heading": "\"Source Serif 4\", Georgia, serif",
    "--font-body": "\"IBM Plex Sans\", system-ui, sans-serif",
    "--space-1": "0.25rem",
    "--space-2": "0.5rem",
    "--space-3": "0.75rem",
    "--space-4": "1rem",
    "--space-6": "1.5rem",
    "--space-8": "2rem",
    "--focus-ring": "0 0 0 3px rgb(37 99 235 / 0.45)",
    "--color-error": "#b91c1c",
    "--color-on-cta": "#ffffff"
  },
  "dark": {
    "--color-primary": "#60a5fa",
    "--color-primary-hover": "#93c5fd",
    "--color-secondary": "#3b82f6",
    "--color-cta": "#ea580c",
    "--color-cta-hover": "#c2410c",
    "--color-bg": "#0f172a",
    "--color-surface": "#1e293b",
    "--color-text": "#f1f5f9",
    "--color-text-muted": "#94a3b8",
    "--color-border": "#334155",
    "--shadow-card": "0 4px 6px -1px rgb(0 0 0 / 0.3)",
    "--radius-md": "12px",
    "--radius-lg": "16px",
    "--font-heading": "\"Source Serif 4\", Georgia, serif",
    "--font-body": "\"IBM Plex Sans\", system-ui, sans-serif",
    "--space-1": "0.25rem",
    "--space-2": "0.5rem",
    "--space-3": "0.75rem",
    "--space-4": "1rem",
    "--space-6": "1.5rem",
    "--space-8": "2rem",
    "--focus-ring": "0 0 0 3px rgb(96 165 250 / 0.5)",
    "--color-error": "#fca5a5",
    "--color-on-cta": "#ffffff"
  }
}
